complexity_estimator/__init__.py
complexity_estimator/cli.py
complexity_estimator/decorators.py
complexity_estimator/estimator.py
complexity_estimator/runtime_profiler.py
complexity_estimator/static_analyzer.py
complexity_estimator_dimple-0.1.2.dist-info/METADATA
complexity_estimator_dimple-0.1.2.dist-info/WHEEL
complexity_estimator_dimple-0.1.2.dist-info/entry_points.txt
complexity_estimator_dimple-0.1.2.dist-info/top_level.txt
complexity_estimator_dimple-0.1.2.dist-info/RECORD
