Metadata-Version: 2.4
Name: complexity-estimator-dimple
Version: 0.1.2
Summary: Estimate time and space complexity of Python functions using static analysis and runtime profiling.
Author: KilariDimple
License-Expression: MIT
Project-URL: Homepage, https://github.com/KilariDimple
Project-URL: Repository, https://github.com/KilariDimple/complexity-estimator-dimple
Keywords: complexity,time complexity,space complexity,Big-O,profiling,static analysis
Requires-Python: >=3.10
Requires-Dist: psutil
